chaosreport/__init__.py
chaosreport/cli.py
chaosreport/template/css/main.css
chaosreport/template/css/normalize.min.css
chaosreport/template/header.md
chaosreport/template/index.md
chaosreport/template/index_to_0.12.2.md
chaosreport/template/index_to_0.15.1.md
chaosreport/template/js/main.js
chaosreport/template/js/vendor/modernizr-2.8.3.min.js
chaostoolkit_reporting-0.18.0.dist-info/METADATA
chaostoolkit_reporting-0.18.0.dist-info/WHEEL
chaostoolkit_reporting-0.18.0.dist-info/entry_points.txt
chaostoolkit_reporting-0.18.0.dist-info/licenses/LICENSE
chaostoolkit_reporting-0.18.0.dist-info/RECORD
