Metadata-Version: 2.1
Name: chaostoolkit-reporting
Version: 0.18.0
Summary: Chaos Toolkit Reporting
Author-Email: Chaos Toolkit Team <contact@chaostoolkit.org>
License: Apache-2.0
Classifier: Development Status :: 4 - Beta
Classifier: Intended Audience :: Developers
Classifier: License :: Freely Distributable
Classifier: License :: OSI Approved :: Apache Software License
Classifier: Operating System :: OS Independent
Classifier: Programming Language :: Python
Classifier: Programming Language :: Python :: 3
Classifier: Programming Language :: Python :: 3.10
Classifier: Programming Language :: Python :: 3.11
Classifier: Programming Language :: Python :: 3.12
Classifier: Programming Language :: Python :: Implementation
Classifier: Programming Language :: Python :: Implementation :: CPython
Project-URL: documentation, https://chaostoolkit.org
Project-URL: repository, https://github.com/chaostoolkit/chaostoolkit-reporting
Project-URL: changelog, https://github.com/chaostoolkit/chaostoolkit-reporting/blob/master/CHANGELOG.md
Requires-Python: >=3.10
Requires-Dist: cairosvg>=2.7.1
Requires-Dist: chaostoolkit-lib>=1.44.0
Requires-Dist: click>=8.1.7
Requires-Dist: dateparser>=1.2.0
Requires-Dist: jinja2>=3.1.4
Requires-Dist: matplotlib>=3.9.3
Requires-Dist: maya>=0.6.1
Requires-Dist: natural>=0.2.0
Requires-Dist: pygal>=3.0.5
Requires-Dist: pypandoc>=1.14
Requires-Dist: semver>=3.0.2
Provides-Extra: ctk
Requires-Dist: chaostoolkit>=1.19.0; extra == "ctk"
